bytedance_grioscontroller/__init__.py
bytedance_grioscontroller-0.0.1.dist-info/METADATA
bytedance_grioscontroller-0.0.1.dist-info/WHEEL
bytedance_grioscontroller-0.0.1.dist-info/top_level.txt
bytedance_grioscontroller-0.0.1.dist-info/RECORD
